jxwechattool/__init__.py
jxwechattool-1.1.0.dist-info/DESCRIPTION.rst
jxwechattool-1.1.0.dist-info/METADATA
jxwechattool-1.1.0.dist-info/RECORD
jxwechattool-1.1.0.dist-info/WHEEL
jxwechattool-1.1.0.dist-info/metadata.json
jxwechattool-1.1.0.dist-info/top_level.txt
