Metadata-Version: 2.0
Name: jxwechattool
Version: 1.1.0
Summary: pywechat access_token qrcode
Home-page: https://jianxun.io
Author: jianxun_dev
Author-email: dev@huntcoder.com
License: Apache License 2.0
Keywords: pywechat access_token qrcode
Platform: UNKNOWN
Requires-Dist: redis
Requires-Dist: requests
